pqm/__init__.py
pqm/_version.py
pqm/pqm.py
pqm/test_gaussian.py
pqm/utils.py
pqm-0.6.3.dist-info/METADATA
pqm-0.6.3.dist-info/WHEEL
pqm-0.6.3.dist-info/licenses/LICENSE
pqm-0.6.3.dist-info/RECORD
