Metadata-Version: 2.4
Name: pqm
Version: 0.6.3
Summary: Implemenation of the PQMass two sample test from Lemos et al. 2024
Project-URL: Homepage, https://github.com/Ciela-Institute/PQM
Project-URL: Documentation, https://github.com/Ciela-Institute/PQM
Project-URL: Repository, https://github.com/Ciela-Institute/PQM
Project-URL: Issues, https://github.com/Ciela-Institute/PQM/issues
Author-email: Pablo Lemos <pablo.lemos@mila.quebec>, Connor Stone <connor.stone@umontreal.ca>, Sammy Sharief <sharief2@illinois.edu>
License: MIT License
License-File: LICENSE
Keywords: machine learning,pytorch,statistics
Classifier: Development Status :: 1 - Planning
Classifier: Intended Audience :: Science/Research
Classifier: License :: OSI Approved :: MIT License
Classifier: Operating System :: OS Independent
Classifier: Programming Language :: Python :: 3
Requires-Python: >=3.9
Requires-Dist: numpy
Requires-Dist: scipy
Requires-Dist: torch
Requires-Dist: tqdm
Provides-Extra: dev
Requires-Dist: pytest-cov<5,>=4.1; extra == 'dev'
Requires-Dist: pytest-mock<4,>=3.12; extra == 'dev'
Requires-Dist: pytest<9,>=8.0; extra == 'dev'
